django_weekend/__init__.py
django_weekend/admin.py
django_weekend/models.py
django_weekend/services.py
django_weekend/migrations/0001_initial.py
django_weekend/migrations/__init__.py
django_weekend-0.0.6.3.dist-info/METADATA
django_weekend-0.0.6.3.dist-info/WHEEL
django_weekend-0.0.6.3.dist-info/top_level.txt
django_weekend-0.0.6.3.dist-info/RECORD
