Metadata-Version: 2.1
Name: django-weekend
Version: 0.0.6.3
Summary: A simple library for tracking weekends and working days
Home-page: https://github.com/MaksimJames/django_weekend
Author: Maksim Prilepsky
Author-email: maksimprilepsky@yandex.ru
License: UNKNOWN
Project-URL: GitHub, https://github.com/MaksimJames/django_weekend
Keywords: django calendar settings weekend
Platform: UNKNOWN
Classifier: Programming Language :: Python :: 3.11
Classifier: License :: OSI Approved :: MIT License
Classifier: Operating System :: OS Independent
Requires-Python: >=3.6
